epyf/__init__.py
epyf/ftbase.cp38-win_amd64.pyd
epyf/ftcore.cp38-win_amd64.pyd
epyf/ftdemo.cp38-win_amd64.pyd
epyf-0.0.1.2022.305.dist-info/LICENSE
epyf-0.0.1.2022.305.dist-info/METADATA
epyf-0.0.1.2022.305.dist-info/WHEEL
epyf-0.0.1.2022.305.dist-info/top_level.txt
epyf-0.0.1.2022.305.dist-info/RECORD
